sqllex/__init__.py
sqllex/classes/__init__.py
sqllex/constants/__init__.py
sqllex/constants/postgresql.py
sqllex/constants/sql.py
sqllex/constants/sqlite.py
sqllex/core/__init__.py
sqllex/core/entities/__init__.py
sqllex/core/entities/abc/__init__.py
sqllex/core/entities/abc/connection.py
sqllex/core/entities/abc/engine.py
sqllex/core/entities/abc/script_gens.py
sqllex/core/entities/abc/sql_column.py
sqllex/core/entities/abc/sql_database.py
sqllex/core/entities/abc/sql_search_condition.py
sqllex/core/entities/abc/sql_transaction.py
sqllex/core/entities/postgresqlx/__init__.py
sqllex/core/entities/postgresqlx/engine.py
sqllex/core/entities/postgresqlx/middleware.py
sqllex/core/entities/postgresqlx/postgresqlx.py
sqllex/core/entities/sqlite3x/__init__.py
sqllex/core/entities/sqlite3x/middleware.py
sqllex/core/entities/sqlite3x/script_gens.py
sqllex/core/entities/sqlite3x/sqlite3x.py
sqllex/core/tools/__init__.py
sqllex/core/tools/convertors/__init__.py
sqllex/core/tools/convertors/crop_size.py
sqllex/core/tools/docs_helpers/__init__.py
sqllex/core/tools/docs_helpers/copy_docs.py
sqllex/core/tools/parsers/__init__.py
sqllex/core/tools/parsers/parsers.py
sqllex/core/tools/sorters/__init__.py
sqllex/core/tools/sorters/column_type.py
sqllex/debug/__init__.py
sqllex/debug/logger.py
sqllex/exceptions/__init__.py
sqllex/exceptions/sqlExceptions.py
sqllex/old/__init__.py
sqllex/old/listers.py
sqllex/types/__init__.py
sqllex/types/types.py
sqllex-0.3.0.post2.dist-info/LICENSE
sqllex-0.3.0.post2.dist-info/METADATA
sqllex-0.3.0.post2.dist-info/WHEEL
sqllex-0.3.0.post2.dist-info/top_level.txt
sqllex-0.3.0.post2.dist-info/RECORD
