Metadata-Version: 2.1
Name: sqllex
Version: 0.3.0.post2
Summary: The most pythonic ORM (for SQLite and PostgreSQL). Seriously, try it out!
Home-page: https://github.com/v1a0/sqllex
Author: v1a0
Author-email: contact@v1a0.dev
License: gpl-3.0
Download-URL: https://github.com/V1A0/sqllex/archive/refs/tags/v0.3.0.post2.tar.gz
Keywords: sqllex,sql,db,database,sqlite3,sqlite,SQLite3,SQLite3x,psycopg2,postgresql,postgres,psql,easy,fast,orm,ORM
Platform: UNKNOWN
Classifier: Development Status :: 3 - Alpha
Classifier: Intended Audience :: Developers
Classifier: Topic :: Database
Classifier: License :: OSI Approved :: GNU General Public License v3 (GPLv3)
Classifier: Programming Language :: Python :: 3.10
Classifier: Programming Language :: Python :: 3.9
Classifier: Programming Language :: Python :: 3.8
License-File: LICENSE
Requires-Dist: loguru (==0.6.0)
